{
	"configurations" : 
	[
		{
			"directories" : 
			[
				{
					"build" : ".",
					"jsonFile" : "directory-.-Debug-f5ebdc15457944623624.json",
					"minimumCMakeVersion" : 
					{
						"string" : "3.26"
					},
					"projectIndex" : 0,
					"source" : ".",
					"targetIndexes" : 
					[
						0
					]
				}
			],
			"name" : "Debug",
			"projects" : 
			[
				{
					"directoryIndexes" : 
					[
						0
					],
					"name" : "longest_common_prefix_easy",
					"targetIndexes" : 
					[
						0
					]
				}
			],
			"targets" : 
			[
				{
					"directoryIndex" : 0,
					"id" : "longest_common_prefix_easy::@6890427a1f51a3e7e1df",
					"jsonFile" : "target-longest_common_prefix_easy-Debug-a4565d4cd3e77901c2b6.json",
					"name" : "longest_common_prefix_easy",
					"projectIndex" : 0
				}
			]
		}
	],
	"kind" : "codemodel",
	"paths" : 
	{
		"build" : "/Users/baonguyen/DEV/leet-code/longest-common-prefix-easy/cmake-build-debug",
		"source" : "/Users/baonguyen/DEV/leet-code/longest-common-prefix-easy"
	},
	"version" : 
	{
		"major" : 2,
		"minor" : 5
	}
}
